AStared/AStared.py
AStared/__init__.py
AStared-0.1.1.dist-info/LICENSE
AStared-0.1.1.dist-info/METADATA
AStared-0.1.1.dist-info/WHEEL
AStared-0.1.1.dist-info/top_level.txt
AStared-0.1.1.dist-info/RECORD
