Metadata-Version: 2.1
Name: AStared
Version: 0.1.1
Summary: AStar python implementatino
Author-email: ThunderTecke <thunder.tecke@gmail.com>
Maintainer-email: ThunderTecke <thunder.tecke@gmail.com>
License: MIT License
Project-URL: Homepage, https://github.com/ThunderTecke/AStared
Project-URL: Bug Tracker, https://github.com/ThunderTecke/AStared/issues
Project-URL: Change log, https://github.com/ThunderTecke/AStared/blob/main/CHANGELOG.md
Keywords: Python,AStar,Algorithm,Pathfinding
Classifier: Development Status :: 4 - Beta
Classifier: Intended Audience :: Developers
Classifier: Intended Audience :: Education
Classifier: Intended Audience :: Science/Research
Classifier: Programming Language :: Python :: 3
Classifier: License :: OSI Approved :: MIT License
Classifier: Operating System :: OS Independent
Requires-Python: >=3.11
License-File: LICENSE
